setup.py
zoe/__init__.py
zoe_py.egg-info/PKG-INFO
zoe_py.egg-info/SOURCES.txt
zoe_py.egg-info/dependency_links.txt
zoe_py.egg-info/top_level.txt