Metadata-Version: 1.0
Name: zoe-py
Version: 0.0.1
Summary: Wait for it!
Home-page: https://github.com/PiotrDabkowski/Zoe
Author: Piotr Dabkowski
Author-email: piodrus@gmail.com
License: MIT
Platform: UNKNOWN
